harbour/__init__.py
harbour/cli.py
harbour/api/__init__.py
harbour/api/execution.py
harbour/api/register.py
harbour/client/__init__.py
harbour/client/artifact.py
harbour/client/object.py
harbour/client/parser.py
harbour/database/__init__.py
harbour/database/table.py
harbour/dynamodb/__init__.py
harbour/hooks/__init__.py
harbour/hooks/build.py
harbour/hooks/push.py
harbour/logger/__init__.py
harbour/storage/__init__.py
harbour/triggers/__init__.py
harbour/triggers/build.py
harbour-0.0.13.dist-info/LICENSE
harbour-0.0.13.dist-info/METADATA
harbour-0.0.13.dist-info/WHEEL
harbour-0.0.13.dist-info/entry_points.txt
harbour-0.0.13.dist-info/top_level.txt
harbour-0.0.13.dist-info/RECORD
